ldap3-stubs/METADATA.toml
ldap3-stubs/__init__.pyi
ldap3-stubs/py.typed
ldap3-stubs/version.pyi
ldap3-stubs/abstract/__init__.pyi
ldap3-stubs/abstract/attrDef.pyi
ldap3-stubs/abstract/attribute.pyi
ldap3-stubs/abstract/cursor.pyi
ldap3-stubs/abstract/entry.pyi
ldap3-stubs/abstract/objectDef.pyi
ldap3-stubs/core/__init__.pyi
ldap3-stubs/core/connection.pyi
ldap3-stubs/core/exceptions.pyi
ldap3-stubs/core/pooling.pyi
ldap3-stubs/core/rdns.pyi
ldap3-stubs/core/results.pyi
ldap3-stubs/core/server.pyi
ldap3-stubs/core/timezone.pyi
ldap3-stubs/core/tls.pyi
ldap3-stubs/core/usage.pyi
ldap3-stubs/extend/__init__.pyi
ldap3-stubs/extend/operation.pyi
ldap3-stubs/extend/microsoft/__init__.pyi
ldap3-stubs/extend/microsoft/addMembersToGroups.pyi
ldap3-stubs/extend/microsoft/dirSync.pyi
ldap3-stubs/extend/microsoft/modifyPassword.pyi
ldap3-stubs/extend/microsoft/persistentSearch.pyi
ldap3-stubs/extend/microsoft/removeMembersFromGroups.pyi
ldap3-stubs/extend/microsoft/unlockAccount.pyi
ldap3-stubs/extend/novell/__init__.pyi
ldap3-stubs/extend/novell/addMembersToGroups.pyi
ldap3-stubs/extend/novell/checkGroupsMemberships.pyi
ldap3-stubs/extend/novell/endTransaction.pyi
ldap3-stubs/extend/novell/getBindDn.pyi
ldap3-stubs/extend/novell/listReplicas.pyi
ldap3-stubs/extend/novell/nmasGetUniversalPassword.pyi
ldap3-stubs/extend/novell/nmasSetUniversalPassword.pyi
ldap3-stubs/extend/novell/partition_entry_count.pyi
ldap3-stubs/extend/novell/removeMembersFromGroups.pyi
ldap3-stubs/extend/novell/replicaInfo.pyi
ldap3-stubs/extend/novell/startTransaction.pyi
ldap3-stubs/extend/standard/PagedSearch.pyi
ldap3-stubs/extend/standard/PersistentSearch.pyi
ldap3-stubs/extend/standard/__init__.pyi
ldap3-stubs/extend/standard/modifyPassword.pyi
ldap3-stubs/extend/standard/whoAmI.pyi
ldap3-stubs/operation/__init__.pyi
ldap3-stubs/operation/abandon.pyi
ldap3-stubs/operation/add.pyi
ldap3-stubs/operation/bind.pyi
ldap3-stubs/operation/compare.pyi
ldap3-stubs/operation/delete.pyi
types_ldap3-2.9.13.20250622.dist-info/licenses/LICENSE
types_ldap3-2.9.13.20250622.dist-info/METADATA
types_ldap3-2.9.13.20250622.dist-info/WHEEL
types_ldap3-2.9.13.20250622.dist-info/top_level.txt
types_ldap3-2.9.13.20250622.dist-info/RECORD
